app/__init__.py
app/api_dgt/__init__.py
app/api_dgt/database_connection.py
app/api_dgt/hazard_index.py
app/api_dgt/incidents_summary.csv
app/api_dgt/modeling_database.py
app/api_dgt/test.ipynb
app/main.py
app/routers/healthz.py
app/routers/hello_world.py
api_python_dgt-0.1.3.dist-info/METADATA
api_python_dgt-0.1.3.dist-info/WHEEL
api_python_dgt-0.1.3.dist-info/RECORD
