Metadata-Version: 2.1
Name: api-python-dgt
Version: 0.1.3
Summary: API-python-dgt
Author: Julio Martinez del Pino
Author-email: juliomdp92@gmail.com
Requires-Python: >=3.11,<3.13
Classifier: Programming Language :: Python :: 3
Classifier: Programming Language :: Python :: 3.11
Classifier: Programming Language :: Python :: 3.12
Requires-Dist: dotenv (==0.9.*)
Requires-Dist: fastapi (==0.111.*)
Requires-Dist: folium (==0.20.*)
Requires-Dist: matplotlib (==3.10.*)
Requires-Dist: pandas (==2.3.*)
Requires-Dist: psycopg2-binary (==2.9.*)
Requires-Dist: python-decouple (==3.8)
Requires-Dist: python-dotenv (==1.2.*)
Requires-Dist: requests (==2.32.*)
Requires-Dist: scikit-learn (==1.8.*)
Requires-Dist: sqlalchemy (==2.0.*)
Requires-Dist: streamlit (==1.53.*)
Requires-Dist: streamlit-folium (==0.26.*)
Requires-Dist: uvicorn[standard] (==0.30.*)
